
{"items":[{"name":"BOOSEGraphicsEnvironment","href":"BOOSEGraphicsEnvironment.html","topicHref":"BOOSEGraphicsEnvironment.html","topicUid":"BOOSEGraphicsEnvironment","type":"Namespace","items":[{"name":"AppCanvas","href":"BOOSEGraphicsEnvironment.AppCanvas.html","topicHref":"BOOSEGraphicsEnvironment.AppCanvas.html","topicUid":"BOOSEGraphicsEnvironment.AppCanvas","type":"Class"},{"name":"AppCommandFactory","href":"BOOSEGraphicsEnvironment.AppCommandFactory.html","topicHref":"BOOSEGraphicsEnvironment.AppCommandFactory.html","topicUid":"BOOSEGraphicsEnvironment.AppCommandFactory","type":"Class"},{"name":"AppForm","href":"BOOSEGraphicsEnvironment.AppForm.html","topicHref":"BOOSEGraphicsEnvironment.AppForm.html","topicUid":"BOOSEGraphicsEnvironment.AppForm","type":"Class"},{"name":"BitmapManager","href":"BOOSEGraphicsEnvironment.BitmapManager.html","topicHref":"BOOSEGraphicsEnvironment.BitmapManager.html","topicUid":"BOOSEGraphicsEnvironment.BitmapManager","type":"Class"},{"name":"IDrawable","href":"BOOSEGraphicsEnvironment.IDrawable.html","topicHref":"BOOSEGraphicsEnvironment.IDrawable.html","topicUid":"BOOSEGraphicsEnvironment.IDrawable","type":"Interface"}]},{"name":"BOOSEGraphicsEnvironment.Commands","href":"BOOSEGraphicsEnvironment.Commands.html","topicHref":"BOOSEGraphicsEnvironment.Commands.html","topicUid":"BOOSEGraphicsEnvironment.Commands","type":"Namespace","items":[{"name":"CircleCommand","href":"BOOSEGraphicsEnvironment.Commands.CircleCommand.html","topicHref":"BOOSEGraphicsEnvironment.Commands.CircleCommand.html","topicUid":"BOOSEGraphicsEnvironment.Commands.CircleCommand","type":"Class"},{"name":"DrawToCommand","href":"BOOSEGraphicsEnvironment.Commands.DrawToCommand.html","topicHref":"BOOSEGraphicsEnvironment.Commands.DrawToCommand.html","topicUid":"BOOSEGraphicsEnvironment.Commands.DrawToCommand","type":"Class"},{"name":"MoveToCommand","href":"BOOSEGraphicsEnvironment.Commands.MoveToCommand.html","topicHref":"BOOSEGraphicsEnvironment.Commands.MoveToCommand.html","topicUid":"BOOSEGraphicsEnvironment.Commands.MoveToCommand","type":"Class"},{"name":"PenColourCommand","href":"BOOSEGraphicsEnvironment.Commands.PenColourCommand.html","topicHref":"BOOSEGraphicsEnvironment.Commands.PenColourCommand.html","topicUid":"BOOSEGraphicsEnvironment.Commands.PenColourCommand","type":"Class"},{"name":"RectCommand","href":"BOOSEGraphicsEnvironment.Commands.RectCommand.html","topicHref":"BOOSEGraphicsEnvironment.Commands.RectCommand.html","topicUid":"BOOSEGraphicsEnvironment.Commands.RectCommand","type":"Class"},{"name":"TriCommand","href":"BOOSEGraphicsEnvironment.Commands.TriCommand.html","topicHref":"BOOSEGraphicsEnvironment.Commands.TriCommand.html","topicUid":"BOOSEGraphicsEnvironment.Commands.TriCommand","type":"Class"}]},{"name":"BOOSEGraphicsEnvironment.Shapes","href":"BOOSEGraphicsEnvironment.Shapes.html","topicHref":"BOOSEGraphicsEnvironment.Shapes.html","topicUid":"BOOSEGraphicsEnvironment.Shapes","type":"Namespace","items":[{"name":"EllipseShape","href":"BOOSEGraphicsEnvironment.Shapes.EllipseShape.html","topicHref":"BOOSEGraphicsEnvironment.Shapes.EllipseShape.html","topicUid":"BOOSEGraphicsEnvironment.Shapes.EllipseShape","type":"Class"},{"name":"PolygonShape","href":"BOOSEGraphicsEnvironment.Shapes.PolygonShape.html","topicHref":"BOOSEGraphicsEnvironment.Shapes.PolygonShape.html","topicUid":"BOOSEGraphicsEnvironment.Shapes.PolygonShape","type":"Class"},{"name":"RectangleShape","href":"BOOSEGraphicsEnvironment.Shapes.RectangleShape.html","topicHref":"BOOSEGraphicsEnvironment.Shapes.RectangleShape.html","topicUid":"BOOSEGraphicsEnvironment.Shapes.RectangleShape","type":"Class"},{"name":"Shape","href":"BOOSEGraphicsEnvironment.Shapes.Shape.html","topicHref":"BOOSEGraphicsEnvironment.Shapes.Shape.html","topicUid":"BOOSEGraphicsEnvironment.Shapes.Shape","type":"Class"}]}],"memberLayout":"SamePage","pdf":false}
